pawel_daily.py
pawel_daily-0.0.1.3.dist-info/LICENSE
pawel_daily-0.0.1.3.dist-info/WHEEL
pawel_daily-0.0.1.3.dist-info/METADATA
pawel_daily-0.0.1.3.dist-info/RECORD
